minorm/__init__.py
minorm/connectors.py
minorm/db_specs.py
minorm/exceptions.py
minorm/expressions.py
minorm/fields.py
minorm/lookups.py
minorm/managers.py
minorm/models.py
minorm/queries.py
minorm/transaction.py
minorm-0.6.0.dist-info/LICENSE.txt
minorm-0.6.0.dist-info/METADATA
minorm-0.6.0.dist-info/WHEEL
minorm-0.6.0.dist-info/top_level.txt
minorm-0.6.0.dist-info/RECORD
