Metadata-Version: 2.1
Name: minorm
Version: 0.6.0
Summary: A minimalistic ORM with basic features.
Home-page: https://github.com/EliasCampos/minorm
Author: Campos Ilya
Author-email: camposylia@gmail.com
License: MIT
Platform: UNKNOWN
Classifier: Development Status :: 2 - Pre-Alpha
Classifier: Intended Audience :: Developers
Classifier: License :: OSI Approved :: MIT License
Classifier: Operating System :: OS Independent
Classifier: Programming Language :: Python
Classifier: Programming Language :: Python :: 3
Classifier: Programming Language :: Python :: 3.6
Classifier: Programming Language :: Python :: 3.7
